[
    {
        "key": "sb",
        "value": "om7tZ2gNEUW004_masIgqewO",
        "domain": "facebook.com",
        "path": "/",
        "hostOnly": false,
        "creation": "2025-04-06T21:00:00.973Z",
        "lastAccessed": "2025-04-06T21:00:00.973Z"
    },
    {
        "key": "ps_l",
        "value": "1",
        "domain": "facebook.com",
        "path": "/",
        "hostOnly": false,
        "creation": "2025-04-06T21:00:00.973Z",
        "lastAccessed": "2025-04-06T21:00:00.973Z"
    },
    {
        "key": "ps_n",
        "value": "1",
        "domain": "facebook.com",
        "path": "/",
        "hostOnly": false,
        "creation": "2025-04-06T21:00:00.973Z",
        "lastAccessed": "2025-04-06T21:00:00.973Z"
    },
    {
        "key": "dpr",
        "value": "1.0994468927383423",
        "domain": "facebook.com",
        "path": "/",
        "hostOnly": false,
        "creation": "2025-04-06T21:00:00.973Z",
        "lastAccessed": "2025-04-06T21:00:00.973Z"
    },
    {
        "key": "locale",
        "value": "en_US",
        "domain": "facebook.com",
        "path": "/",
        "hostOnly": false,
        "creation": "2025-04-06T21:00:00.973Z",
        "lastAccessed": "2025-04-06T21:00:00.973Z"
    },
    {
        "key": "datr",
        "value": "9OTyZ9A0dQQCe3i5JtGJsPqA",
        "domain": "facebook.com",
        "path": "/",
        "hostOnly": false,
        "creation": "2025-04-06T21:00:00.973Z",
        "lastAccessed": "2025-04-06T21:00:00.973Z"
    },
    {
        "key": "c_user",
        "value": "100032644512844",
        "domain": "facebook.com",
        "path": "/",
        "hostOnly": false,
        "creation": "2025-04-06T21:00:00.973Z",
        "lastAccessed": "2025-04-06T21:00:00.973Z"
    },
    {
        "key": "wd",
        "value": "800x1160",
        "domain": "facebook.com",
        "path": "/",
        "hostOnly": false,
        "creation": "2025-04-06T21:00:00.973Z",
        "lastAccessed": "2025-04-06T21:00:00.973Z"
    },
    {
        "key": "fr",
        "value": "1YcgtMzMP2n9H5FbJ.AWe3655dWTYyHtVQ5I6lydbMNj6f9lIqkDNxeCrohCVRbocv5RM.Bn8us1..AAA.0.0.Bn8us1.AWf2_bC3IduXXr7qaSU9aDVZm6k",
        "domain": "facebook.com",
        "path": "/",
        "hostOnly": false,
        "creation": "2025-04-06T21:00:00.973Z",
        "lastAccessed": "2025-04-06T21:00:00.973Z"
    },
    {
        "key": "xs",
        "value": "9%3ABd7bLZnJndHedw%3A2%3A1743971996%3A-1%3A12235%3A%3AAcW8vzAPHjA52maJm_W8Fjw-ouM9eQ7TEqh3QhQjNw",
        "domain": "facebook.com",
        "path": "/",
        "hostOnly": false,
        "creation": "2025-04-06T21:00:00.973Z",
        "lastAccessed": "2025-04-06T21:00:00.973Z"
    },
    {
        "key": "presence",
        "value": "C%7B%22lm3%22%3A%22g.24112390098349398%22%2C%22t3%22%3A%5B%5D%2C%22utc3%22%3A1743973200528%2C%22v%22%3A1%7D",
        "domain": "facebook.com",
        "path": "/",
        "hostOnly": false,
        "creation": "2025-04-06T21:00:00.973Z",
        "lastAccessed": "2025-04-06T21:00:00.973Z"
    }
]
